carDemo/__init__.py
carDemo11-0.0.1.dist-info/METADATA
carDemo11-0.0.1.dist-info/WHEEL
carDemo11-0.0.1.dist-info/top_level.txt
carDemo11-0.0.1.dist-info/RECORD
