Metadata-Version: 2.1
Name: carDemo11
Version: 0.0.1
Summary: send car data to socket
Author: baoxukang
Author-email: xukang.bao@high-genius.com
License: apache 3.0
Classifier: Development Status :: 3 - Alpha
Classifier: Intended Audience :: Developers
Classifier: License :: OSI Approved :: MIT License
Classifier: Programming Language :: Python :: 3
Classifier: Programming Language :: Python :: 3.6
Classifier: Programming Language :: Python :: 3.7
Classifier: Programming Language :: Python :: 3.8
Requires-Python: >=3.6
